[
  {
    "title": "Software Engineer",
    "description": "I am a software engineer with a passion for building scalable and efficient software solutions. I have experience working with various programming languages, frameworks, and tools, including Java, Python, JavaScript, and TypeScript. I am proficient in web development, particularly with React and Node.js.",
    "startDate": "2022-01-01",
    "endDate": "2024-12-31",
    "location": "Remote",
    "skills": [
      "JavaScript",
      "React",
      "Node.js",
      "TypeScript",
      "HTML",
      "CSS",
      "Git",
      "RESTful APIs",
      "Web Development",
      "Databases",
      "Unit Testing",
      "Continuous Integration",
      "Version Control",
      "Agile Methodologies",
      "Project Management",
      "Communication",
      "Team Collaboration",
      "Problem Solving",
      "Leadership",
      "Time Management",
      "Conflict Resolution",
      "Negotiation",
      "Adaptability",
      "Resilience",
      "Empathy",
      "Collaboration",
      "Creativity",
      "Innovation",
      "Self-awareness",
      "Open-mindedness",
      "Curiosity",
      "Persistence",
      "Passion",
      "Perseverance",
      "Adaptability",
      "Flexibility",
      "Ability to learn quickly",
      "Ability to work"
    ]
  },
  {
    "title": "Full Stack Developer",
    "description": "I am a full stack developer with a passion for building scalable and efficient software solutions. I have experience working with various programming languages, frameworks, and tools, including Java, Python, JavaScript, and TypeScript. I am proficient in web development, particularly with React and Node.js.",
    "startDate": "2022-01-01",
    "endDate": "2022-12-31",
    "location": "Remote",
    "skills": [
      "JavaScript",
      "React",
      "Node.js",
      "TypeScript",
      "HTML",
      "CSS",
      "Git",
      "RESTful APIs",
      "Web Development",
      "Databases",
      "Unit Testing",
      "Continuous Integration",
      "Version Control",
      "Agile Methodologies",
      "Project Management",
      "Communication",
      "Team Collaboration",
      "Problem Solving",
      "Leadership",
      "Time Management",
      "Conflict Resolution",
      "Negotiation",
      "Adaptability",
      "Resilience",
      "Empathy",
      "Collaboration",
      "Creativity",
      "Innovation",
      "Self-awareness",
      "Open-mindedness",
      "Curiosity",
      "Persistence",
      "Passion",
      "Perseverance",
      "Adaptability",
      "Flexibility",
      "Ability to learn quickly"
    ]
  }
]
